frame_generator_with_flow_control.v
module frame_generator_with_flow_control(
    output reg [9:0] frame_data_with_sync,  // Frame data + Start/Stop bits
    input wire clk,                          // Clock input
    input wire reset,                        // Reset input
    input wire start,                        // Start signal for frame generation
    input wire flow_control_enable,          // Enable flow control (Pause Frame)
    input wire [7:0] frame_data_in0,         // Frame data byte 0
    input wire [7:0] frame_data_in1,         // Frame data byte 1
    input wire [7:0] frame_data_in2,         // Frame data byte 2
    input wire [7:0] frame_data_in3,         // Frame data byte 3
    input wire [7:0] frame_data_in4,         // Frame data byte 4
    input wire [7:0] frame_data_in5,         // Frame data byte 5
    input wire [7:0] frame_data_in6,         // Frame data byte 6
    input wire [7:0] frame_data_in7,         // Frame data byte 7
    input wire [7:0] frame_data_in8,         // Frame data byte 8
    input wire [7:0] frame_data_in9,         // Frame data byte 9
    input wire [7:0] frame_data_in10,        // Frame data byte 10
    input wire [7:0] frame_data_in11,        // Frame data byte 11
    input wire [7:0] frame_data_in12,        // Frame data byte 12
    input wire [7:0] frame_data_in13,        // Frame data byte 13
    input wire [7:0] frame_data_in14,        // Frame data byte 14
    input wire [7:0] frame_data_in15         // Frame data byte 15
);

    reg [3:0] byte_counter;                 // Byte counter to track frame progress
    reg transmitting;                        // Flag for transmission
    reg start_bit;                           // Start bit (low-active)
    reg stop_bit;                            // Stop bit (high-active)
    
    // Always block to control frame generation and add start/stop bits
    always @(posedge clk or posedge reset) begin
        if (reset) begin
            frame_data_with_sync <= 10'h000;
            byte_counter <= 4'b0000;
            transmitting <= 1'b0;
            start_bit <= 1'b0;   // Start bit (0)
            stop_bit <= 1'b1;    // Stop bit (1)
        end else if (start && !transmitting && !flow_control_enable) begin
            transmitting <= 1'b1;
            byte_counter <= 4'b0000;  // Start from first byte
        end else if (flow_control_enable) begin
            // Pause Frame generation (simple case)
            // Pause frame is a special frame with specific type 0x8808
            frame_data_with_sync <= {stop_bit, 8'h00, 8'h00, start_bit}; // Using the pause frame data
            transmitting <= 1'b0;  // Stop transmission after sending pause frame
        end else if (transmitting) begin
            // Insert start bit before the frame byte and stop bit after
            case(byte_counter)
                4'b0000: frame_data_with_sync <= {stop_bit, frame_data_in0, start_bit};
                4'b0001: frame_data_with_sync <= {stop_bit, frame_data_in1, start_bit};
                4'b0010: frame_data_with_sync <= {stop_bit, frame_data_in2, start_bit};
                4'b0011: frame_data_with_sync <= {stop_bit, frame_data_in3, start_bit};
                4'b0100: frame_data_with_sync <= {stop_bit, frame_data_in4, start_bit};
                4'b0101: frame_data_with_sync <= {stop_bit, frame_data_in5, start_bit};
                4'b0110: frame_data_with_sync <= {stop_bit, frame_data_in6, start_bit};
                4'b0111: frame_data_with_sync <= {stop_bit, frame_data_in7, start_bit};
                4'b1000: frame_data_with_sync <= {stop_bit, frame_data_in8, start_bit};
                4'b1001: frame_data_with_sync <= {stop_bit, frame_data_in9, start_bit};
                4'b1010: frame_data_with_sync <= {stop_bit, frame_data_in10, start_bit};
                4'b1011: frame_data_with_sync <= {stop_bit, frame_data_in11, start_bit};
                4'b1100: frame_data_with_sync <= {stop_bit, frame_data_in12, start_bit};
                4'b1101: frame_data_with_sync <= {stop_bit, frame_data_in13, start_bit};
                4'b1110: frame_data_with_sync <= {stop_bit, frame_data_in14, start_bit};
                4'b1111: frame_data_with_sync <= {stop_bit, frame_data_in15, start_bit};
                default: frame_data_with_sync <= 10'h000;
            endcase

            byte_counter <= byte_counter + 1;
            if (byte_counter == 4'b1111) begin
                transmitting <= 1'b0;  // End transmission
            end
        end
    end
endmodule

frame_generator_with_flow_control_tb.v
module frame_generator_with_flow_control_tb;

    reg clk;
    reg reset;
    reg start;
    reg flow_control_enable;
    reg [7:0] frame_data_in0, frame_data_in1, frame_data_in2, frame_data_in3, frame_data_in4;
    reg [7:0] frame_data_in5, frame_data_in6, frame_data_in7, frame_data_in8, frame_data_in9;
    reg [7:0] frame_data_in10, frame_data_in11, frame_data_in12, frame_data_in13, frame_data_in14;
    reg [7:0] frame_data_in15;
    wire [9:0] frame_data_with_sync;

    // Instantiate frame generator with flow control
    frame_generator_with_flow_control uut (
        .clk(clk),
        .reset(reset),
        .start(start),
        .flow_control_enable(flow_control_enable),
        .frame_data_in0(frame_data_in0),
        .frame_data_in1(frame_data_in1),
        .frame_data_in2(frame_data_in2),
        .frame_data_in3(frame_data_in3),
        .frame_data_in4(frame_data_in4),
        .frame_data_in5(frame_data_in5),
        .frame_data_in6(frame_data_in6),
        .frame_data_in7(frame_data_in7),
        .frame_data_in8(frame_data_in8),
        .frame_data_in9(frame_data_in9),
        .frame_data_in10(frame_data_in10),
        .frame_data_in11(frame_data_in11),
        .frame_data_in12(frame_data_in12),
        .frame_data_in13(frame_data_in13),
        .frame_data_in14(frame_data_in14),
        .frame_data_in15(frame_data_in15),
        .frame_data_with_sync(frame_data_with_sync)
    );

    // Clock generation
    always begin
        #5 clk = ~clk;
    end

    // VCD Dump
    initial begin
        // Open VCD file for waveform dump
        $dumpfile("frame_generator_with_flow_control_tb.vcd");
        $dumpvars(0, frame_generator_with_flow_control_tb);

        // Initialize signals
        clk = 0;
        reset = 0;
        start = 0;
        flow_control_enable = 0;
        frame_data_in0 = 8'hAA; frame_data_in1 = 8'hBB; frame_data_in2 = 8'hCC;
        frame_data_in3 = 8'hDD; frame_data_in4 = 8'hEE; frame_data_in5 = 8'hFF;
        frame_data_in6 = 8'h01; frame_data_in7 = 8'h02; frame_data_in8 = 8'h03;
        frame_data_in9 = 8'h04; frame_data_in10 = 8'h05; frame_data_in11 = 8'h06;
        frame_data_in12 = 8'h07; frame_data_in13 = 8'h08; frame_data_in14 = 8'h09;
        frame_data_in15 = 8'h10;

        // Test sequence
        reset = 1; #10 reset = 0; // Apply reset
        start = 1; #10 start = 0;  // Start transmission
        #100 flow_control_enable = 1; // Enable flow control after 100ns
        #50 flow_control_enable = 0;  // Disable flow control

        // Finish the simulation after a while
        #200 $finish;
    end

endmodule

frame_gen_with_flow_control.vcd
$date
	Sat Nov 30 14:04:59 2024
$end
$version
	Icarus Verilog
$end
$timescale
	1s
$end
$scope module frame_generator_with_flow_control_tb $end
$var wire 10 ! frame_data_with_sync [9:0] $end
$var reg 1 " clk $end
$var reg 1 # flow_control_enable $end
$var reg 8 $ frame_data_in0 [7:0] $end
$var reg 8 % frame_data_in1 [7:0] $end
$var reg 8 & frame_data_in10 [7:0] $end
$var reg 8 ' frame_data_in11 [7:0] $end
$var reg 8 ( frame_data_in12 [7:0] $end
$var reg 8 ) frame_data_in13 [7:0] $end
$var reg 8 * frame_data_in14 [7:0] $end
$var reg 8 + frame_data_in15 [7:0] $end
$var reg 8 , frame_data_in2 [7:0] $end
$var reg 8 - frame_data_in3 [7:0] $end
$var reg 8 . frame_data_in4 [7:0] $end
$var reg 8 / frame_data_in5 [7:0] $end
$var reg 8 0 frame_data_in6 [7:0] $end
$var reg 8 1 frame_data_in7 [7:0] $end
$var reg 8 2 frame_data_in8 [7:0] $end
$var reg 8 3 frame_data_in9 [7:0] $end
$var reg 1 4 reset $end
$var reg 1 5 start $end
$scope module uut $end
$var wire 1 " clk $end
$var wire 1 # flow_control_enable $end
$var wire 8 6 frame_data_in0 [7:0] $end
$var wire 8 7 frame_data_in1 [7:0] $end
$var wire 8 8 frame_data_in10 [7:0] $end
$var wire 8 9 frame_data_in11 [7:0] $end
$var wire 8 : frame_data_in12 [7:0] $end
$var wire 8 ; frame_data_in13 [7:0] $end
$var wire 8 < frame_data_in14 [7:0] $end
$var wire 8 = frame_data_in15 [7:0] $end
$var wire 8 > frame_data_in2 [7:0] $end
$var wire 8 ? frame_data_in3 [7:0] $end
$var wire 8 @ frame_data_in4 [7:0] $end
$var wire 8 A frame_data_in5 [7:0] $end
$var wire 8 B frame_data_in6 [7:0] $end
$var wire 8 C frame_data_in7 [7:0] $end
$var wire 8 D frame_data_in8 [7:0] $end
$var wire 8 E frame_data_in9 [7:0] $end
$var wire 1 4 reset $end
$var wire 1 5 start $end
$var reg 4 F byte_counter [3:0] $end
$var reg 10 G frame_data_with_sync [9:0] $end
$var reg 1 H start_bit $end
$var reg 1 I stop_bit $end
$var reg 1 J transmitting $end
$upscope $end
$upscope $end
$enddefinitions $end
$comment Show the parameter values. $end
$dumpall
$end
#0
$dumpvars
0J
1I
0H
b0 G
b0 F
b100 E
b11 D
b10 C
b1 B
b11111111 A
b11101110 @
b11011101 ?
b11001100 >
b10000 =
b1001 <
b1000 ;
b111 :
b110 9
b101 8
b10111011 7
b10101010 6
05
14
b100 3
b11 2
b10 1
b1 0
b11111111 /
b11101110 .
b11011101 -
b11001100 ,
b10000 +
b1001 *
b1000 )
b111 (
b110 '
b101 &
b10111011 %
b10101010 $
0#
0"
b0 !
$end
#5
1"
#10
0"
15
04
#15
1J
1"
#20
0"
05
#25
b1 F
b1101010100 !
b1101010100 G
1"
#30
0"
#35
b10 F
b1101110110 !
b1101110110 G
1"
#40
0"
#45
b11 F
b1110011000 !
b1110011000 G
1"
#50
0"
#55
b100 F
b1110111010 !
b1110111010 G
1"
#60
0"
#65
b101 F
b1111011100 !
b1111011100 G
1"
#70
0"
#75
b110 F
b1111111110 !
b1111111110 G
1"
#80
0"
#85
b111 F
b1000000010 !
b1000000010 G
1"
#90
0"
#95
b1000 F
b1000000100 !
b1000000100 G
1"
#100
0"
#105
b1001 F
b1000000110 !
b1000000110 G
1"
#110
0"
#115
b1010 F
b1000001000 !
b1000001000 G
1"
#120
0"
1#
#125
0J
b0 !
b0 G
1"
#130
0"
#135
1"
#140
0"
#145
1"
#150
0"
#155
1"
#160
0"
#165
1"
#170
0"
0#
