frame_generator.v
module frame_generator(
    output reg [7:0] frame_data,  // Frame data output
    output reg [7:0] crc,         // CRC output
    input wire clk,                // Clock input
    input wire reset,              // Reset input
    input wire start,              // Start frame generation signal
    input wire [7:0] frame_data_in0, // Frame data byte 0
    input wire [7:0] frame_data_in1, // Frame data byte 1
    input wire [7:0] frame_data_in2, // Frame data byte 2
    input wire [7:0] frame_data_in3, // Frame data byte 3
    input wire [7:0] frame_data_in4, // Frame data byte 4
    input wire [7:0] frame_data_in5, // Frame data byte 5
    input wire [7:0] frame_data_in6, // Frame data byte 6
    input wire [7:0] frame_data_in7, // Frame data byte 7
    input wire [7:0] frame_data_in8, // Frame data byte 8
    input wire [7:0] frame_data_in9, // Frame data byte 9
    input wire [7:0] frame_data_in10, // Frame data byte 10
    input wire [7:0] frame_data_in11, // Frame data byte 11
    input wire [7:0] frame_data_in12, // Frame data byte 12
    input wire [7:0] frame_data_in13, // Frame data byte 13
    input wire [7:0] frame_data_in14, // Frame data byte 14
    input wire [7:0] frame_data_in15  // Frame data byte 15
);

    reg [3:0] byte_counter;        // Byte counter to track which byte to send
    reg transmitting;              // Flag to indicate whether frame transmission is ongoing

    // CRC calculation logic (example: simple XOR CRC calculation)
    always @(posedge clk or posedge reset) begin
        if (reset) begin
            crc <= 8'h00;  // Initialize CRC to 0 on reset
        end else if (transmitting) begin
            crc <= crc ^ frame_data;  // Simple XOR CRC calculation (not a real CRC algorithm)
        end
    end

    // Frame generation logic
    always @(posedge clk or posedge reset) begin
        if (reset) begin
            frame_data <= 8'h00;
            byte_counter <= 4'b0000;
            transmitting <= 1'b0;
        end else if (start && !transmitting) begin
            transmitting <= 1'b1;
            byte_counter <= 4'b0000;  // Start from the first byte of the frame
        end else if (transmitting) begin
            // Output current byte of the frame using case statements to select the byte based on byte_counter
            case(byte_counter)
                4'b0000: frame_data <= frame_data_in0;
                4'b0001: frame_data <= frame_data_in1;
                4'b0010: frame_data <= frame_data_in2;
                4'b0011: frame_data <= frame_data_in3;
                4'b0100: frame_data <= frame_data_in4;
                4'b0101: frame_data <= frame_data_in5;
                4'b0110: frame_data <= frame_data_in6;
                4'b0111: frame_data <= frame_data_in7;
                4'b1000: frame_data <= frame_data_in8;
                4'b1001: frame_data <= frame_data_in9;
                4'b1010: frame_data <= frame_data_in10;
                4'b1011: frame_data <= frame_data_in11;
                4'b1100: frame_data <= frame_data_in12;
                4'b1101: frame_data <= frame_data_in13;
                4'b1110: frame_data <= frame_data_in14;
                4'b1111: frame_data <= frame_data_in15;
                default: frame_data <= 8'h00; // Default case to reset if something goes wrong
            endcase

            byte_counter <= byte_counter + 1;  // Increment byte counter
            if (byte_counter == 4'b1111) begin  // After the last byte
                transmitting <= 1'b0;          // Stop transmission
            end
        end
    end
endmodule

frame_generator_tb.v
module frame_generator_tb;

    // Testbench signals
    reg clk;
    reg reset;
    reg start;
    reg [7:0] frame_data_in0, frame_data_in1, frame_data_in2, frame_data_in3;
    reg [7:0] frame_data_in4, frame_data_in5, frame_data_in6, frame_data_in7;
    reg [7:0] frame_data_in8, frame_data_in9, frame_data_in10, frame_data_in11;
    reg [7:0] frame_data_in12, frame_data_in13, frame_data_in14, frame_data_in15;
    wire [7:0] frame_data;
    wire [7:0] crc;

    // Instantiate the frame generator module
    frame_generator uut (
        .frame_data(frame_data),
        .crc(crc),
        .clk(clk),
        .reset(reset),
        .start(start),
        .frame_data_in0(frame_data_in0),
        .frame_data_in1(frame_data_in1),
        .frame_data_in2(frame_data_in2),
        .frame_data_in3(frame_data_in3),
        .frame_data_in4(frame_data_in4),
        .frame_data_in5(frame_data_in5),
        .frame_data_in6(frame_data_in6),
        .frame_data_in7(frame_data_in7),
        .frame_data_in8(frame_data_in8),
        .frame_data_in9(frame_data_in9),
        .frame_data_in10(frame_data_in10),
        .frame_data_in11(frame_data_in11),
        .frame_data_in12(frame_data_in12),
        .frame_data_in13(frame_data_in13),
        .frame_data_in14(frame_data_in14),
        .frame_data_in15(frame_data_in15)
    );

    // Clock generation
    always begin
        #5 clk = ~clk;  // 10ns clock period
    end

    // Test sequence
    initial begin
        // Initialize signals
        clk = 0;
        reset = 0;
        start = 0;
        frame_data_in0 = 8'h01; frame_data_in1 = 8'h02; frame_data_in2 = 8'h03; frame_data_in3 = 8'h04;
        frame_data_in4 = 8'h05; frame_data_in5 = 8'h06; frame_data_in6 = 8'h07; frame_data_in7 = 8'h08;
        frame_data_in8 = 8'h09; frame_data_in9 = 8'h0A; frame_data_in10 = 8'h0B; frame_data_in11 = 8'h0C;
        frame_data_in12 = 8'h0D; frame_data_in13 = 8'h0E; frame_data_in14 = 8'h0F; frame_data_in15 = 8'h10;

        // Reset the DUT
        reset = 1;
        #10 reset = 0;

        // Start frame generation
        start = 1;
        #10 start = 0;

        // Wait for a few cycles to let the frame generation complete
        #160;

        // End of simulation
        $finish;
    end

    // Dump the waveform (including frame_data and crc)
    initial begin
        $dumpfile("frame_generator_tb.vcd");
        $dumpvars(0, frame_generator_tb);
    end
endmodule

frame_generator_tb.vcd
$date
	Sat Nov 30 13:04:59 2024
$end
$version
	Icarus Verilog
$end
$timescale
	1s
$end
$scope module frame_generator_tb $end
$var wire 8 ! frame_data [7:0] $end
$var wire 8 " crc [7:0] $end
$var reg 1 # clk $end
$var reg 8 $ frame_data_in0 [7:0] $end
$var reg 8 % frame_data_in1 [7:0] $end
$var reg 8 & frame_data_in10 [7:0] $end
$var reg 8 ' frame_data_in11 [7:0] $end
$var reg 8 ( frame_data_in12 [7:0] $end
$var reg 8 ) frame_data_in13 [7:0] $end
$var reg 8 * frame_data_in14 [7:0] $end
$var reg 8 + frame_data_in15 [7:0] $end
$var reg 8 , frame_data_in2 [7:0] $end
$var reg 8 - frame_data_in3 [7:0] $end
$var reg 8 . frame_data_in4 [7:0] $end
$var reg 8 / frame_data_in5 [7:0] $end
$var reg 8 0 frame_data_in6 [7:0] $end
$var reg 8 1 frame_data_in7 [7:0] $end
$var reg 8 2 frame_data_in8 [7:0] $end
$var reg 8 3 frame_data_in9 [7:0] $end
$var reg 1 4 reset $end
$var reg 1 5 start $end
$scope module uut $end
$var wire 1 # clk $end
$var wire 8 6 frame_data_in0 [7:0] $end
$var wire 8 7 frame_data_in1 [7:0] $end
$var wire 8 8 frame_data_in10 [7:0] $end
$var wire 8 9 frame_data_in11 [7:0] $end
$var wire 8 : frame_data_in12 [7:0] $end
$var wire 8 ; frame_data_in13 [7:0] $end
$var wire 8 < frame_data_in14 [7:0] $end
$var wire 8 = frame_data_in15 [7:0] $end
$var wire 8 > frame_data_in2 [7:0] $end
$var wire 8 ? frame_data_in3 [7:0] $end
$var wire 8 @ frame_data_in4 [7:0] $end
$var wire 8 A frame_data_in5 [7:0] $end
$var wire 8 B frame_data_in6 [7:0] $end
$var wire 8 C frame_data_in7 [7:0] $end
$var wire 8 D frame_data_in8 [7:0] $end
$var wire 8 E frame_data_in9 [7:0] $end
$var wire 1 4 reset $end
$var wire 1 5 start $end
$var reg 4 F byte_counter [3:0] $end
$var reg 8 G crc [7:0] $end
$var reg 8 H frame_data [7:0] $end
$var reg 1 I transmitting $end
$upscope $end
$upscope $end
$enddefinitions $end
$comment Show the parameter values. $end
$dumpall
$end
#0
$dumpvars
0I
b0 H
b0 G
b0 F
b1010 E
b1001 D
b1000 C
b111 B
b110 A
b101 @
b100 ?
b11 >
b10000 =
b1111 <
b1110 ;
b1101 :
b1100 9
b1011 8
b10 7
b1 6
05
14
b1010 3
b1001 2
b1000 1
b111 0
b110 /
b101 .
b100 -
b11 ,
b10000 +
b1111 *
b1110 )
b1101 (
b1100 '
b1011 &
b10 %
b1 $
0#
b0 "
b0 !
$end
#5
1#
#10
0#
15
04
#15
1I
1#
#20
0#
05
#25
b1 F
b1 !
b1 H
1#
#30
0#
#35
b1 "
b1 G
b10 F
b10 !
b10 H
1#
#40
0#
#45
b11 F
b11 !
b11 H
b11 "
b11 G
1#
#50
0#
#55
b0 "
b0 G
b100 F
b100 !
b100 H
1#
#60
0#
#65
b101 F
b101 !
b101 H
b100 "
b100 G
1#
#70
0#
#75
b1 "
b1 G
b110 F
b110 !
b110 H
1#
#80
0#
#85
b111 F
b111 !
b111 H
b111 "
b111 G
1#
#90
0#
#95
b0 "
b0 G
b1000 F
b1000 !
b1000 H
1#
#100
0#
#105
b1001 F
b1001 !
b1001 H
b1000 "
b1000 G
1#
#110
0#
#115
b1 "
b1 G
b1010 F
b1010 !
b1010 H
1#
#120
0#
#125
b1011 F
b1011 !
b1011 H
b1011 "
b1011 G
1#
#130
0#
#135
b0 "
b0 G
b1100 F
b1100 !
b1100 H
1#
#140
0#
#145
b1101 F
b1101 !
b1101 H
b1100 "
b1100 G
1#
#150
0#
#155
b1 "
b1 G
b1110 F
b1110 !
b1110 H
1#
#160
0#
#165
b1111 F
b1111 !
b1111 H
b1111 "
b1111 G
1#
#170
0#
#175
b0 "
b0 G
0I
b0 F
b10000 !
b10000 H
1#
